pipctl/__about__.py
pipctl/__init__.py
pipctl/__main__.py
pipctl/_config.py
pipctl/_constraint.py
pipctl/_exceptions.py
pipctl/_osv.py
pipctl/cli.py
pipctl/data/configSchema.json
pipctl/data/templateConfig.yaml
pipctl-0.0.0.dist-info/LICENSE
pipctl-0.0.0.dist-info/METADATA
pipctl-0.0.0.dist-info/WHEEL
pipctl-0.0.0.dist-info/entry_points.txt
pipctl-0.0.0.dist-info/top_level.txt
pipctl-0.0.0.dist-info/RECORD
