Metadata-Version: 2.1
Name: pipctl
Version: 0.0.0
Summary: Control pip's resolution process
Home-page: https://github.com/fridex/pipctl
Author: Fridolin Pokorny
Author-email: fridolin.pokorny@datadoghq.com
Maintainer: Fridolin Pokorny
Maintainer-email: fridolin.pokorny@datadoghq.com
License: BSD-3-Clause
Download-URL: https://pypi.org/project/pipctl/
Keywords: packaging,pip,dependencies,dependency-management,utilities,vulnerabilities,security,pip-tools
Platform: UNKNOWN
Classifier: Development Status :: 1 - Planning
Classifier: Intended Audience :: Developers
Classifier: License :: OSI Approved :: Apache Software License
Classifier: Programming Language :: Python
Classifier: Programming Language :: Python :: 3.9
Classifier: Programming Language :: Python :: 3.10
Classifier: Programming Language :: Python :: 3.11
Classifier: Programming Language :: Python :: Implementation :: CPython
Requires-Python: >=3.9
License-File: LICENSE
Requires-Dist: attrs
Requires-Dist: click
Requires-Dist: daiquiri
Requires-Dist: micropipenv
Requires-Dist: pyyaml
Requires-Dist: requests
Requires-Dist: rich-click
Requires-Dist: openapi-schema-validator
Requires-Dist: pip-tools
Requires-Dist: pip-requirements-parser
Provides-Extra: testing
Requires-Dist: pytest ; extra == 'testing'
